privacy/qa/commons/win/__init__.py
privacy.qa.commons.win-0.0.2.dist-info/METADATA
privacy.qa.commons.win-0.0.2.dist-info/WHEEL
privacy.qa.commons.win-0.0.2.dist-info/top_level.txt
privacy.qa.commons.win-0.0.2.dist-info/RECORD
